exc_motherclass/aboutproject.py
exc_motherclass/motherclass.py
exc_motherclass-0.0.0.dist-info/LICENSE
exc_motherclass-0.0.0.dist-info/WHEEL
exc_motherclass-0.0.0.dist-info/METADATA
exc_motherclass-0.0.0.dist-info/RECORD
