Metadata-Version: 2.1
Name: exc-motherclass
Version: 0.0.0
Summary: 
License: GPLv3
Author: suizokukan
Author-email: suizokukan@orange.fr
Requires-Python: >=3.9,<4.0
Classifier: License :: Other/Proprietary License
Classifier: Programming Language :: Python :: 3
Classifier: Programming Language :: Python :: 3.10
Classifier: Programming Language :: Python :: 3.9
Requires-Dist: exc-errors (>=0.0.0,<0.0.1)
Requires-Dist: iaswn (>=0.1.6,<0.2.0)
